fancytypes/__init__.py
fancytypes/version.py
fancytypes-1.0.2.dist-info/licenses/LICENSE
fancytypes-1.0.2.dist-info/METADATA
fancytypes-1.0.2.dist-info/WHEEL
fancytypes-1.0.2.dist-info/top_level.txt
fancytypes-1.0.2.dist-info/RECORD
